{"Addiction": [
  {
    "count": 1,
    "word": "vibe"
  },
  {
    "count": 1,
    "word": "been"
  },
  {
    "count": 4,
    "word": "bad"
  },
  {
    "count": 4,
    "word": "told"
  },
  {
    "count": 3,
    "word": "don't"
  },
  {
    "count": 1,
    "word": "what's"
  },
  {
    "count": 2,
    "word": "about"
  },
  {
    "count": 2,
    "word": "cocoming"
  },
  {
    "count": 4,
    "word": "your"
  },
  {
    "count": 1,
    "word": "spontaneous"
  },
  {
    "count": 1,
    "word": "three"
  },
  {
    "count": 3,
    "word": "when"
  },
  {
    "count": 1,
    "word": "put"
  },
  {
    "count": 8,
    "word": "tried"
  },
  {
    "count": 1,
    "word": "drunk"
  },
  {
    "count": 1,
    "word": "credibly"
  },
  {
    "count": 6,
    "word": "would"
  },
  {
    "count": 3,
    "word": "her"
  },
  {
    "count": 4,
    "word": "let"
  },
  {
    "count": 1,
    "word": "catch"
  },
  {
    "count": 1,
    "word": "if"
  },
  {
    "count": 25,
    "word": "you"
  },
  {
    "count": 4,
    "word": "they"
  },
  {
    "count": 1,
    "word": "there's"
  },
  {
    "count": 3,
    "word": "okay"
  },
  {
    "count": 1,
    "word": "in"
  },
  {
    "count": 9,
    "word": "is"
  },
  {
    "count": 6,
    "word": "it"
  },
  {
    "count": 3,
    "word": "then"
  },
  {
    "count": 2,
    "word": "doja"
  },
  {
    "count": 1,
    "word": "doors"
  },
  {
    "count": 1,
    "word": "hypothetically"
  },
  {
    "count": 1,
    "word": "ever"
  },
  {
    "count": 1,
    "word": "as"
  },
  {
    "count": 4,
    "word": "stop"
  },
  {
    "count": 2,
    "word": "wanted"
  },
  {
    "count": 2,
    "word": "uhh"
  },
  {
    "count": 1,
    "word": "guess"
  },
  {
    "count": 1,
    "word": "turning"
  },
  {
    "count": 1,
    "word": "i've"
  },
  {
    "count": 8,
    "word": "be"
  },
  {
    "count": 1,
    "word": "maybe"
  },
  {
    "count": 1,
    "word": "essence"
  },
  {
    "count": 2,
    "word": "roll"
  },
  {
    "count": 1,
    "word": "afflicted"
  },
  {
    "count": 1,
    "word": "two"
  },
  {
    "count": 1,
    "word": "eyes"
  },
  {
    "count": 1,
    "word": "thinking"
  },
  {
    "count": 5,
    "word": "i'm"
  },
  {
    "count": 1,
    "word": "remember"
  },
  {
    "count": 1,
    "word": "into"
  },
  {
    "count": 1,
    "word": "how"
  },
  {
    "count": 1,
    "word": "gon'"
  },
  {
    "count": 1,
    "word": "see"
  },
  {
    "count": 1,
    "word": "same"
  },
  {
    "count": 1,
    "word": "time's"
  },
  {
    "count": 1,
    "word": "unless"
  },
  {
    "count": 1,
    "word": "by"
  },
  {
    "count": 4,
    "word": "get"
  },
  {
    "count": 3,
    "word": "she's"
  },
  {
    "count": 8,
    "word": "man"
  },
  {
    "count": 8,
    "word": "everything"
  },
  {
    "count": 9,
    "word": "so"
  },
  {
    "count": 1,
    "word": "means"
  },
  {
    "count": 3,
    "word": "a"
  },
  {
    "count": 1,
    "word": "drugs"
  },
  {
    "count": 6,
    "word": "could"
  },
  {
    "count": 1,
    "word": "more"
  },
  {
    "count": 1,
    "word": "lover"
  },
  {
    "count": 3,
    "word": "one"
  },
  {
    "count": 35,
    "word": "i"
  },
  {
    "count": 1,
    "word": "blown"
  },
  {
    "count": 1,
    "word": "right"
  },
  {
    "count": 1,
    "word": "somethin'"
  },
  {
    "count": 1,
    "word": "peek"
  },
  {
    "count": 17,
    "word": "the"
  },
  {
    "count": 1,
    "word": "emotion"
  },
  {
    "count": 2,
    "word": "henny"
  },
  {
    "count": 1,
    "word": "ask"
  },
  {
    "count": 1,
    "word": "closed"
  },
  {
    "count": 19,
    "word": "to"
  },
  {
    "count": 1,
    "word": "thing"
  },
  {
    "count": 7,
    "word": "but"
  },
  {
    "count": 1,
    "word": "cocococa"
  },
  {
    "count": 4,
    "word": "feel"
  },
  {
    "count": 1,
    "word": "lotion"
  },
  {
    "count": 1,
    "word": "girls"
  },
  {
    "count": 2,
    "word": "do"
  },
  {
    "count": 4,
    "word": "good"
  },
  {
    "count": 2,
    "word": "got"
  },
  {
    "count": 12,
    "word": "smile"
  },
  {
    "count": 2,
    "word": "'cause"
  },
  {
    "count": 3,
    "word": "that"
  },
  {
    "count": 2,
    "word": "high"
  },
  {
    "count": 27,
    "word": "me"
  },
  {
    "count": 1,
    "word": "lust"
  },
  {
    "count": 1,
    "word": "um"
  },
  {
    "count": 1,
    "word": "undress"
  },
  {
    "count": 2,
    "word": "up"
  },
  {
    "count": 1,
    "word": "us"
  },
  {
    "count": 2,
    "word": "all"
  },
  {
    "count": 1,
    "word": "curious"
  },
  {
    "count": 2,
    "word": "need"
  },
  {
    "count": 1,
    "word": "pose"
  },
  {
    "count": 2,
    "word": "it's"
  },
  {
    "count": 2,
    "word": "let's"
  },
  {
    "count": 1,
    "word": "addiction"
  },
  {
    "count": 2,
    "word": "this"
  },
  {
    "count": 1,
    "word": "seriously"
  },
  {
    "count": 1,
    "word": "feeling"
  },
  {
    "count": 5,
    "word": "my"
  },
  {
    "count": 5,
    "word": "heart"
  },
  {
    "count": 1,
    "word": "ohh"
  },
  {
    "count": 1,
    "word": "friends"
  },
  {
    "count": 1,
    "word": "both"
  },
  {
    "count": 2,
    "word": "nenever"
  },
  {
    "count": 1,
    "word": "she"
  },
  {
    "count": 2,
    "word": "take"
  },
  {
    "count": 1,
    "word": "keep"
  },
  {
    "count": 4,
    "word": "supposed"
  },
  {
    "count": 1,
    "word": "know"
  },
  {
    "count": 1,
    "word": "try"
  },
  {
    "count": 1,
    "word": "thighs"
  },
  {
    "count": 1,
    "word": "no"
  },
  {
    "count": 1,
    "word": "show"
  },
  {
    "count": 4,
    "word": "why"
  },
  {
    "count": 1,
    "word": "back"
  },
  {
    "count": 4,
    "word": "that's"
  },
  {
    "count": 4,
    "word": "best"
  },
  {
    "count": 3,
    "word": "we"
  },
  {
    "count": 1,
    "word": "cocococacola"
  },
  {
    "count": 1,
    "word": "cola"
  },
  {
    "count": 9,
    "word": "not"
  },
  {
    "count": 1,
    "word": "kidding"
  },
  {
    "count": 1,
    "word": "impose"
  },
  {
    "count": 8,
    "word": "and"
  },
  {
    "count": 5,
    "word": "now"
  },
  {
    "count": 1,
    "word": "of"
  },
  {
    "count": 1,
    "word": "oh"
  },
  {
    "count": 1,
    "word": "lies"
  },
  {
    "count": 1,
    "word": "exposed"
  },
  {
    "count": 1,
    "word": "weed"
  },
  {
    "count": 1,
    "word": "said"
  },
  {
    "count": 16,
    "word": "make"
  },
  {
    "count": 6,
    "word": "just"
  },
  {
    "count": 5,
    "word": "over"
  },
  {
    "count": 1,
    "word": "potion"
  },
  {
    "count": 2,
    "word": "or"
  },
  {
    "count": 1,
    "word": "pour"
  },
  {
    "count": 1,
    "word": "go"
  },
  {
    "count": 2,
    "word": "was"
  },
  {
    "count": 1,
    "word": "say"
  },
  {
    "count": 4,
    "word": "exactly"
  },
  {
    "count": 1,
    "word": "rush"
  },
  {
    "count": 1,
    "word": "i'll"
  },
  {
    "count": 1,
    "word": "damn"
  },
  {
    "count": 5,
    "word": "with"
  },
  {
    "count": 4,
    "word": "what"
  },
  {
    "count": 1,
    "word": "money"
  },
  {
    "count": 1,
    "word": "incredibly"
  },
  {
    "count": 8,
    "word": "mean"
  },
  {
    "count": 2,
    "word": "baby"
  },
  {
    "count": 1,
    "word": "well"
  },
  {
    "count": 1,
    "word": "coming"
  },
  {
    "count": 1,
    "word": "closest"
  }
]}
