{"GunzComeOut": [
  {
    "count": 1,
    "word": "exception"
  },
  {
    "count": 1,
    "word": "projects"
  },
  {
    "count": 4,
    "word": "don't"
  },
  {
    "count": 1,
    "word": "brownsville"
  },
  {
    "count": 8,
    "word": "about"
  },
  {
    "count": 1,
    "word": "infrared"
  },
  {
    "count": 11,
    "word": "your"
  },
  {
    "count": 1,
    "word": "fighting"
  },
  {
    "count": 2,
    "word": "fucking"
  },
  {
    "count": 1,
    "word": "promised"
  },
  {
    "count": 1,
    "word": "flatbush"
  },
  {
    "count": 2,
    "word": "homie"
  },
  {
    "count": 1,
    "word": "bind"
  },
  {
    "count": 1,
    "word": "brooklyn"
  },
  {
    "count": 1,
    "word": "flatline"
  },
  {
    "count": 1,
    "word": "let"
  },
  {
    "count": 2,
    "word": "welcome"
  },
  {
    "count": 8,
    "word": "dough"
  },
  {
    "count": 4,
    "word": "they"
  },
  {
    "count": 18,
    "word": "you"
  },
  {
    "count": 1,
    "word": "spray"
  },
  {
    "count": 1,
    "word": "peeled"
  },
  {
    "count": 18,
    "word": "then"
  },
  {
    "count": 1,
    "word": "scrilla"
  },
  {
    "count": 1,
    "word": "thug"
  },
  {
    "count": 1,
    "word": "blowing"
  },
  {
    "count": 1,
    "word": "at"
  },
  {
    "count": 1,
    "word": "stop"
  },
  {
    "count": 1,
    "word": "ar15"
  },
  {
    "count": 1,
    "word": "22"
  },
  {
    "count": 2,
    "word": "cut"
  },
  {
    "count": 1,
    "word": "be"
  },
  {
    "count": 1,
    "word": "another"
  },
  {
    "count": 1,
    "word": "roll"
  },
  {
    "count": 1,
    "word": "hop"
  },
  {
    "count": 2,
    "word": "dead"
  },
  {
    "count": 1,
    "word": "long"
  },
  {
    "count": 1,
    "word": "pop"
  },
  {
    "count": 2,
    "word": "how"
  },
  {
    "count": 1,
    "word": "see"
  },
  {
    "count": 1,
    "word": "search"
  },
  {
    "count": 1,
    "word": "are"
  },
  {
    "count": 3,
    "word": "so"
  },
  {
    "count": 1,
    "word": "hand"
  },
  {
    "count": 1,
    "word": "mine"
  },
  {
    "count": 12,
    "word": "a"
  },
  {
    "count": 1,
    "word": "think"
  },
  {
    "count": 1,
    "word": "mind"
  },
  {
    "count": 1,
    "word": "hoopty"
  },
  {
    "count": 1,
    "word": "one"
  },
  {
    "count": 1,
    "word": "makes"
  },
  {
    "count": 9,
    "word": "i"
  },
  {
    "count": 1,
    "word": "maker"
  },
  {
    "count": 1,
    "word": "blood"
  },
  {
    "count": 1,
    "word": "food"
  },
  {
    "count": 36,
    "word": "the"
  },
  {
    "count": 1,
    "word": "call"
  },
  {
    "count": 1,
    "word": "pull"
  },
  {
    "count": 1,
    "word": "entering"
  },
  {
    "count": 1,
    "word": "veins"
  },
  {
    "count": 1,
    "word": "hollows"
  },
  {
    "count": 2,
    "word": "blue"
  },
  {
    "count": 1,
    "word": "meet"
  },
  {
    "count": 1,
    "word": "thang"
  },
  {
    "count": 1,
    "word": "clap"
  },
  {
    "count": 1,
    "word": "calf"
  },
  {
    "count": 1,
    "word": "progress"
  },
  {
    "count": 7,
    "word": "to"
  },
  {
    "count": 1,
    "word": "inch"
  },
  {
    "count": 2,
    "word": "ass"
  },
  {
    "count": 3,
    "word": "but"
  },
  {
    "count": 1,
    "word": "through"
  },
  {
    "count": 1,
    "word": "nine"
  },
  {
    "count": 1,
    "word": "instinct"
  },
  {
    "count": 1,
    "word": "clips"
  },
  {
    "count": 1,
    "word": "ice"
  },
  {
    "count": 4,
    "word": "run"
  },
  {
    "count": 1,
    "word": "gangstas"
  },
  {
    "count": 1,
    "word": "language"
  },
  {
    "count": 1,
    "word": "do"
  },
  {
    "count": 2,
    "word": "down"
  },
  {
    "count": 2,
    "word": "got"
  },
  {
    "count": 1,
    "word": "hat"
  },
  {
    "count": 1,
    "word": "talk"
  },
  {
    "count": 1,
    "word": "shoot"
  },
  {
    "count": 4,
    "word": "up"
  },
  {
    "count": 2,
    "word": "murder"
  },
  {
    "count": 1,
    "word": "chrome"
  },
  {
    "count": 2,
    "word": "this"
  },
  {
    "count": 1,
    "word": "look"
  },
  {
    "count": 1,
    "word": "respect"
  },
  {
    "count": 31,
    "word": "y'all"
  },
  {
    "count": 1,
    "word": "once"
  },
  {
    "count": 1,
    "word": "shell"
  },
  {
    "count": 1,
    "word": "llamas"
  },
  {
    "count": 1,
    "word": "gunshot"
  },
  {
    "count": 45,
    "word": "know"
  },
  {
    "count": 2,
    "word": "little"
  },
  {
    "count": 1,
    "word": "trust"
  },
  {
    "count": 2,
    "word": "some"
  },
  {
    "count": 1,
    "word": "doing"
  },
  {
    "count": 1,
    "word": "away"
  },
  {
    "count": 2,
    "word": "for"
  },
  {
    "count": 1,
    "word": "back"
  },
  {
    "count": 1,
    "word": "rule"
  },
  {
    "count": 6,
    "word": "cold"
  },
  {
    "count": 1,
    "word": "we"
  },
  {
    "count": 1,
    "word": "life"
  },
  {
    "count": 1,
    "word": "187's"
  },
  {
    "count": 2,
    "word": "killa"
  },
  {
    "count": 1,
    "word": "now"
  },
  {
    "count": 2,
    "word": "you're"
  },
  {
    "count": 1,
    "word": "scope"
  },
  {
    "count": 1,
    "word": "bloods"
  },
  {
    "count": 1,
    "word": "soften"
  },
  {
    "count": 1,
    "word": "hard"
  },
  {
    "count": 16,
    "word": "whatwhat"
  },
  {
    "count": 2,
    "word": "just"
  },
  {
    "count": 1,
    "word": "human"
  },
  {
    "count": 36,
    "word": "niggas"
  },
  {
    "count": 1,
    "word": "we'll"
  },
  {
    "count": 1,
    "word": "go"
  },
  {
    "count": 1,
    "word": "windows"
  },
  {
    "count": 1,
    "word": "killed"
  },
  {
    "count": 1,
    "word": "i'll"
  },
  {
    "count": 1,
    "word": "way"
  },
  {
    "count": 1,
    "word": "semiauto"
  },
  {
    "count": 1,
    "word": "hole"
  },
  {
    "count": 16,
    "word": "with"
  },
  {
    "count": 1,
    "word": "dime"
  },
  {
    "count": 8,
    "word": "what"
  },
  {
    "count": 1,
    "word": "money"
  },
  {
    "count": 1,
    "word": "crips"
  },
  {
    "count": 2,
    "word": "time"
  },
  {
    "count": 1,
    "word": "he"
  },
  {
    "count": 1,
    "word": "play"
  },
  {
    "count": 17,
    "word": "guns"
  },
  {
    "count": 5,
    "word": "ya"
  },
  {
    "count": 1,
    "word": "exterminate"
  },
  {
    "count": 1,
    "word": "when"
  },
  {
    "count": 1,
    "word": "tips"
  },
  {
    "count": 6,
    "word": "'em"
  },
  {
    "count": 1,
    "word": "outy'all"
  },
  {
    "count": 1,
    "word": "problem"
  },
  {
    "count": 1,
    "word": "karate"
  },
  {
    "count": 1,
    "word": "stuck"
  },
  {
    "count": 2,
    "word": "if"
  },
  {
    "count": 3,
    "word": "case"
  },
  {
    "count": 1,
    "word": "crown"
  },
  {
    "count": 2,
    "word": "there's"
  },
  {
    "count": 1,
    "word": "dumbass"
  },
  {
    "count": 2,
    "word": "still"
  },
  {
    "count": 10,
    "word": "in"
  },
  {
    "count": 1,
    "word": "suicide"
  },
  {
    "count": 1,
    "word": "contract"
  },
  {
    "count": 1,
    "word": "tomorrow"
  },
  {
    "count": 1,
    "word": "hollow"
  },
  {
    "count": 17,
    "word": "come"
  },
  {
    "count": 2,
    "word": "is"
  },
  {
    "count": 1,
    "word": "it"
  },
  {
    "count": 1,
    "word": "hood"
  },
  {
    "count": 2,
    "word": "wanna"
  },
  {
    "count": 1,
    "word": "heavy"
  },
  {
    "count": 1,
    "word": "doors"
  },
  {
    "count": 1,
    "word": "finna"
  },
  {
    "count": 1,
    "word": "system"
  },
  {
    "count": 1,
    "word": "phone"
  },
  {
    "count": 1,
    "word": "macs"
  },
  {
    "count": 1,
    "word": "cooling"
  },
  {
    "count": 1,
    "word": "crazy"
  },
  {
    "count": 1,
    "word": "jungle"
  },
  {
    "count": 1,
    "word": "love"
  },
  {
    "count": 1,
    "word": "gun"
  },
  {
    "count": 1,
    "word": "tussle"
  },
  {
    "count": 1,
    "word": "against"
  },
  {
    "count": 10,
    "word": "fuck"
  },
  {
    "count": 1,
    "word": "range"
  },
  {
    "count": 16,
    "word": "i'm"
  },
  {
    "count": 20,
    "word": "out"
  },
  {
    "count": 1,
    "word": "low"
  },
  {
    "count": 1,
    "word": "too"
  },
  {
    "count": 1,
    "word": "accommodate"
  },
  {
    "count": 5,
    "word": "get"
  },
  {
    "count": 1,
    "word": "eat"
  },
  {
    "count": 1,
    "word": "share"
  },
  {
    "count": 1,
    "word": "chain"
  },
  {
    "count": 1,
    "word": "bread"
  },
  {
    "count": 1,
    "word": "lover"
  },
  {
    "count": 1,
    "word": "bought"
  },
  {
    "count": 3,
    "word": "cool"
  },
  {
    "count": 1,
    "word": "blown"
  },
  {
    "count": 1,
    "word": "kill"
  },
  {
    "count": 1,
    "word": "lead"
  },
  {
    "count": 1,
    "word": "whereabouts"
  },
  {
    "count": 1,
    "word": "future"
  },
  {
    "count": 1,
    "word": "cutting"
  },
  {
    "count": 1,
    "word": "tonight"
  },
  {
    "count": 1,
    "word": "terrordome"
  },
  {
    "count": 1,
    "word": "use"
  },
  {
    "count": 1,
    "word": "own"
  },
  {
    "count": 1,
    "word": "sign"
  },
  {
    "count": 2,
    "word": "feel"
  },
  {
    "count": 3,
    "word": "that"
  },
  {
    "count": 1,
    "word": "brains"
  },
  {
    "count": 5,
    "word": "hit"
  },
  {
    "count": 1,
    "word": "split"
  },
  {
    "count": 1,
    "word": "pussy"
  },
  {
    "count": 1,
    "word": "zone"
  },
  {
    "count": 2,
    "word": "find"
  },
  {
    "count": 4,
    "word": "me"
  },
  {
    "count": 1,
    "word": "grain"
  },
  {
    "count": 1,
    "word": "day"
  },
  {
    "count": 2,
    "word": "all"
  },
  {
    "count": 4,
    "word": "new"
  },
  {
    "count": 1,
    "word": "bitch"
  },
  {
    "count": 1,
    "word": "lay"
  },
  {
    "count": 4,
    "word": "it's"
  },
  {
    "count": 4,
    "word": "touch"
  },
  {
    "count": 1,
    "word": "real"
  },
  {
    "count": 15,
    "word": "my"
  },
  {
    "count": 1,
    "word": "heart"
  },
  {
    "count": 1,
    "word": "plus"
  },
  {
    "count": 2,
    "word": "feed"
  },
  {
    "count": 2,
    "word": "keep"
  },
  {
    "count": 1,
    "word": "try"
  },
  {
    "count": 1,
    "word": "behind"
  },
  {
    "count": 3,
    "word": "no"
  },
  {
    "count": 1,
    "word": "game"
  },
  {
    "count": 1,
    "word": "death"
  },
  {
    "count": 1,
    "word": "hoes"
  },
  {
    "count": 1,
    "word": "cause"
  },
  {
    "count": 1,
    "word": "their"
  },
  {
    "count": 1,
    "word": "niggas'll"
  },
  {
    "count": 2,
    "word": "around"
  },
  {
    "count": 1,
    "word": "boy"
  },
  {
    "count": 1,
    "word": "wolves"
  },
  {
    "count": 3,
    "word": "head"
  },
  {
    "count": 1,
    "word": "can"
  },
  {
    "count": 1,
    "word": "cap"
  },
  {
    "count": 1,
    "word": "car"
  },
  {
    "count": 10,
    "word": "and"
  },
  {
    "count": 1,
    "word": "ready"
  },
  {
    "count": 1,
    "word": "of"
  },
  {
    "count": 1,
    "word": "extra"
  },
  {
    "count": 1,
    "word": "muffled"
  },
  {
    "count": 10,
    "word": "nigga"
  },
  {
    "count": 1,
    "word": "bust"
  },
  {
    "count": 1,
    "word": "zoo"
  },
  {
    "count": 3,
    "word": "on"
  },
  {
    "count": 1,
    "word": "bricks"
  },
  {
    "count": 1,
    "word": "or"
  },
  {
    "count": 2,
    "word": "will"
  },
  {
    "count": 1,
    "word": "say"
  },
  {
    "count": 1,
    "word": "rolls"
  },
  {
    "count": 1,
    "word": "drill"
  },
  {
    "count": 1,
    "word": "shine"
  },
  {
    "count": 1,
    "word": "heights"
  },
  {
    "count": 2,
    "word": "york"
  },
  {
    "count": 2,
    "word": "walk"
  }
]}
